{"commitInfo":{"timestamp":1753238649284,"operation":"WRITE","operationParameters":{"mode":"Overwrite","partitionBy":"[\"coin_id\",\"date\"]"},"readVersion":46,"isolationLevel":"Serializable","isBlindAppend":false,"operationMetrics":{"numFiles":"2","numOutputRows":"224","numOutputBytes":"5295"},"engineInfo":"Apache-Spark/3.4.3 Delta-Lake/2.4.0","txnId":"79d07d4a-8f19-4dcb-8056-b8e5aa2a4624"}}
{"add":{"path":"coin_id=bitcoin/date=2025-07-22/part-00000-12e1f031-0447-4ef1-9b6a-a3a178455363.c000.snappy.parquet","partitionValues":{"coin_id":"bitcoin","date":"2025-07-22"},"size":4279,"modificationTime":1753238649186,"dataChange":true,"stats":"{\"numRecords\":207,\"minValues\":{\"timestamp\":\"2025-07-22T01:51:36.853Z\",\"price\":116836.06927714494},\"maxValues\":{\"timestamp\":\"2025-07-22T23:57:23.318Z\",\"price\":120222.24496007951},\"nullCount\":{\"timestamp\":0,\"price\":0}}"}}
{"add":{"path":"coin_id=bitcoin/date=2025-07-23/part-00000-f3c28ada-63f2-4203-89e8-fc53e3c54fbd.c000.snappy.parquet","partitionValues":{"coin_id":"bitcoin","date":"2025-07-23"},"size":1016,"modificationTime":1753238649193,"dataChange":true,"stats":"{\"numRecords\":17,\"minValues\":{\"timestamp\":\"2025-07-23T00:04:16.006Z\",\"price\":119525.54291316475},\"maxValues\":{\"timestamp\":\"2025-07-23T01:52:13.000Z\",\"price\":119958.86217219132},\"nullCount\":{\"timestamp\":0,\"price\":0}}"}}
{"remove":{"path":"coin_id=bitcoin/date=2025-07-23/part-00000-f299849b-69b3-4493-a59a-5975872bbf0a.c000.snappy.parquet","deletionTimestamp":1753238649284,"dataChange":true,"extendedFileMetadata":true,"partitionValues":{"coin_id":"bitcoin","date":"2025-07-23"},"size":1032}}
{"remove":{"path":"coin_id=bitcoin/date=2025-07-22/part-00000-3be711f6-516a-4c1f-98cf-bd750d80c7ae.c000.snappy.parquet","deletionTimestamp":1753238649284,"dataChange":true,"extendedFileMetadata":true,"partitionValues":{"coin_id":"bitcoin","date":"2025-07-22"},"size":4247}}
