{"commitInfo":{"timestamp":1753237985852,"operation":"WRITE","operationParameters":{"mode":"Overwrite","partitionBy":"[\"coin_id\",\"date\"]"},"readVersion":9,"isolationLevel":"Serializable","isBlindAppend":false,"operationMetrics":{"numFiles":"2","numOutputRows":"246","numOutputBytes":"5670"},"engineInfo":"Apache-Spark/3.4.3 Delta-Lake/2.4.0","txnId":"78a2a0d3-8626-4533-bce0-8211a743d8ca"}}
{"add":{"path":"coin_id=bitcoin/date=2025-07-21/part-00000-e0a5f256-f7a6-4c63-ba9a-748ed6c0ab9d.c000.snappy.parquet","partitionValues":{"coin_id":"bitcoin","date":"2025-07-21"},"size":1590,"modificationTime":1753237985522,"dataChange":true,"stats":"{\"numRecords\":51,\"minValues\":{\"timestamp\":\"2025-07-21T19:45:27.038Z\",\"volume\":4.493711759822101E10},\"maxValues\":{\"timestamp\":\"2025-07-21T23:56:37.764Z\",\"volume\":5.3533161641603294E10},\"nullCount\":{\"timestamp\":0,\"volume\":0}}"}}
{"add":{"path":"coin_id=bitcoin/date=2025-07-22/part-00000-ab983e01-6eea-4d2f-98a3-05edc5c3212c.c000.snappy.parquet","partitionValues":{"coin_id":"bitcoin","date":"2025-07-22"},"size":4080,"modificationTime":1753237985541,"dataChange":true,"stats":"{\"numRecords\":195,\"minValues\":{\"timestamp\":\"2025-07-22T00:00:44.472Z\",\"volume\":3.944947569301442E10},\"maxValues\":{\"timestamp\":\"2025-07-22T19:41:05.000Z\",\"volume\":5.8936259064470345E10},\"nullCount\":{\"timestamp\":0,\"volume\":0}}"}}
{"remove":{"path":"coin_id=bitcoin/date=2025-07-22/part-00000-6426ad0a-3dda-4405-b6bc-b9005c4e099e.c000.snappy.parquet","deletionTimestamp":1753237985852,"dataChange":true,"extendedFileMetadata":true,"partitionValues":{"coin_id":"bitcoin","date":"2025-07-22"},"size":4321}}
{"remove":{"path":"coin_id=bitcoin/date=2025-07-23/part-00000-e6647326-d087-4ab7-9ce8-6474fd2304ac.c000.snappy.parquet","deletionTimestamp":1753237985852,"dataChange":true,"extendedFileMetadata":true,"partitionValues":{"coin_id":"bitcoin","date":"2025-07-23"},"size":979}}
