{"commitInfo":{"timestamp":1753237966931,"operation":"WRITE","operationParameters":{"mode":"Overwrite","partitionBy":"[\"coin_id\",\"date\"]"},"readVersion":5,"isolationLevel":"Serializable","isBlindAppend":false,"operationMetrics":{"numFiles":"2","numOutputRows":"221","numOutputBytes":"5243"},"engineInfo":"Apache-Spark/3.4.3 Delta-Lake/2.4.0","txnId":"bbad9bf5-adf0-4c47-8f0e-224e75b4db3a"}}
{"add":{"path":"coin_id=ethereum/date=2025-07-22/part-00000-84770277-4520-4bfb-b92c-1e4d5effeee2.c000.snappy.parquet","partitionValues":{"coin_id":"ethereum","date":"2025-07-22"},"size":4211,"modificationTime":1753237966859,"dataChange":true,"stats":"{\"numRecords\":203,\"minValues\":{\"timestamp\":\"2025-07-22T02:15:27.112Z\",\"volume\":3.4223027143730312E10},\"maxValues\":{\"timestamp\":\"2025-07-22T23:57:25.195Z\",\"volume\":5.656888942385696E10},\"nullCount\":{\"timestamp\":0,\"volume\":0}}"}}
{"add":{"path":"coin_id=ethereum/date=2025-07-23/part-00000-0029af57-2832-4425-8ba3-88316c830d60.c000.snappy.parquet","partitionValues":{"coin_id":"ethereum","date":"2025-07-23"},"size":1032,"modificationTime":1753237966865,"dataChange":true,"stats":"{\"numRecords\":18,\"minValues\":{\"timestamp\":\"2025-07-23T00:03:57.157Z\",\"volume\":4.142919051451055E10},\"maxValues\":{\"timestamp\":\"2025-07-23T02:15:55.000Z\",\"volume\":5.35419370362117E10},\"nullCount\":{\"timestamp\":0,\"volume\":0}}"}}
{"remove":{"path":"coin_id=ethereum/date=2025-07-21/part-00000-e6545197-4ae9-4715-8593-157618904bde.c000.snappy.parquet","deletionTimestamp":1753237966931,"dataChange":true,"extendedFileMetadata":true,"partitionValues":{"coin_id":"ethereum","date":"2025-07-21"},"size":1622}}
{"remove":{"path":"coin_id=ethereum/date=2025-07-22/part-00000-25189e16-549f-4cef-a430-3b75c2cad720.c000.snappy.parquet","deletionTimestamp":1753237966931,"dataChange":true,"extendedFileMetadata":true,"partitionValues":{"coin_id":"ethereum","date":"2025-07-22"},"size":4071}}
