{"commitInfo":{"timestamp":1753240153833,"operation":"WRITE","operationParameters":{"mode":"Overwrite","partitionBy":"[\"coin_id\",\"date\"]"},"readVersion":118,"isolationLevel":"Serializable","isBlindAppend":false,"operationMetrics":{"numFiles":"2","numOutputRows":"220","numOutputBytes":"5223"},"engineInfo":"Apache-Spark/3.4.3 Delta-Lake/2.4.0","txnId":"efefa436-edcf-42ec-97a3-bdb15878b0d6"}}
{"add":{"path":"coin_id=ethereum/date=2025-07-22/part-00000-aee3e52f-cf00-406f-8bc1-6fd2b6da57b4.c000.snappy.parquet","partitionValues":{"coin_id":"ethereum","date":"2025-07-22"},"size":4140,"modificationTime":1753240153742,"dataChange":true,"stats":"{\"numRecords\":199,\"minValues\":{\"timestamp\":\"2025-07-22T02:36:52.026Z\",\"volume\":3.4223027143730312E10},\"maxValues\":{\"timestamp\":\"2025-07-22T23:57:25.195Z\",\"volume\":5.656888942385696E10},\"nullCount\":{\"timestamp\":0,\"volume\":0}}"}}
{"add":{"path":"coin_id=ethereum/date=2025-07-23/part-00000-16ed4029-f989-4e08-89eb-9a61014d03ab.c000.snappy.parquet","partitionValues":{"coin_id":"ethereum","date":"2025-07-23"},"size":1083,"modificationTime":1753240153750,"dataChange":true,"stats":"{\"numRecords\":21,\"minValues\":{\"timestamp\":\"2025-07-23T00:03:57.157Z\",\"volume\":4.142919051451055E10},\"maxValues\":{\"timestamp\":\"2025-07-23T02:35:27.000Z\",\"volume\":5.35419370362117E10},\"nullCount\":{\"timestamp\":0,\"volume\":0}}"}}
{"remove":{"path":"coin_id=ethereum/date=2025-07-21/part-00000-a119c8e7-af9b-4e5a-a25d-0404d1568d5d.c000.snappy.parquet","deletionTimestamp":1753240153833,"dataChange":true,"extendedFileMetadata":true,"partitionValues":{"coin_id":"ethereum","date":"2025-07-21"},"size":1608}}
{"remove":{"path":"coin_id=ethereum/date=2025-07-22/part-00000-62b82a82-200a-478d-9424-23f64eccf6a8.c000.snappy.parquet","deletionTimestamp":1753240153833,"dataChange":true,"extendedFileMetadata":true,"partitionValues":{"coin_id":"ethereum","date":"2025-07-22"},"size":4087}}
